iictl/__init__.py
iictl/__main__.py
iictl/main.py
iictl/bin/darwin/kubectl
iictl/bin/linux/kubectl
iictl/bin/windows/kubectl.exe
iictl/commands/__init__.py
iictl/commands/attach.py
iictl/commands/cp.py
iictl/commands/exec.py
iictl/commands/logs.py
iictl/commands/main.py
iictl/commands/ps.py
iictl/commands/resources.py
iictl/commands/rm.py
iictl/commands/run.py
iictl/commands/config/__init__.py
iictl/commands/config/main.py
iictl/commands/config/get/__init__.py
iictl/commands/config/get/main.py
iictl/commands/config/get/namespace.py
iictl/commands/config/set/__init__.py
iictl/commands/config/set/main.py
iictl/commands/config/set/namespace.py
iictl/commands/registry/__init__.py
iictl/commands/registry/auth.py
iictl/commands/registry/ls.py
iictl/commands/registry/main.py
iictl/commands/registry/rm.py
iictl/commands/volume/__init__.py
iictl/commands/volume/create.py
iictl/commands/volume/ls.py
iictl/commands/volume/main.py
iictl/commands/volume/protect.py
iictl/commands/volume/rm.py
iictl/commands/volume/unprotect.py
iictl/crud/__init__.py
iictl/crud/event.py
iictl/crud/integrated_instance.py
iictl/crud/node.py
iictl/crud/persistent_volume_claim.py
iictl/crud/pod.py
iictl/crud/secret.py
iictl/crud/stream.py
iictl/crud/tools.py
iictl/format/__init__.py
iictl/format/integrated_instance.py
iictl/format/persistent_volume_claim.py
iictl/format/secret.py
iictl/kubectl/__init__.py
iictl/kubectl/kubectl.py
iictl/utils/__init__.py
iictl/utils/click.py
iictl/utils/exception.py
iictl/utils/kube.py
iictl/utils/parse.py
iictl/utils/shell_executor.py
iictl-0.0.1.15.dist-info/METADATA
iictl-0.0.1.15.dist-info/WHEEL
iictl-0.0.1.15.dist-info/entry_points.txt
iictl-0.0.1.15.dist-info/top_level.txt
iictl-0.0.1.15.dist-info/RECORD
